frond/__init__.py
frond-0.0.4.dist-info/METADATA
frond-0.0.4.dist-info/RECORD
frond-0.0.4.dist-info/WHEEL
frond-0.0.4.dist-info/top_level.txt
