Metadata-Version: 2.1
Name: frond
Version: 0.0.4
Summary: Asynchronous Fan Out/In for Pyramid.
Home-page: https://gitlab.com/landreville/frond
Author: Landreville
Author-email: landreville@heyneat.ca
License: UNKNOWN
Platform: UNKNOWN
Classifier: Programming Language :: Python
Classifier: Programming Language :: Python :: 3 :: Only
Classifier: Framework :: Pyramid
Classifier: Topic :: Internet :: WWW/HTTP
Classifier: License :: OSI Approved :: MIT License
